setup.py
distributions1_probability/Binomialdistribution.py
distributions1_probability/Gaussiandistribution.py
distributions1_probability/Generaldistribution.py
distributions1_probability/__init__.py
distributions1_probability.egg-info/PKG-INFO
distributions1_probability.egg-info/SOURCES.txt
distributions1_probability.egg-info/dependency_links.txt
distributions1_probability.egg-info/not-zip-safe
distributions1_probability.egg-info/top_level.txt