Metadata-Version: 1.0
Name: distributions1-probability
Version: 1.0
Summary: Gaussian and Binomial distributions
Home-page: UNKNOWN
Author: Eddy Caldas
Author-email: eddycaldas@live.com
License: UNKNOWN
Platform: UNKNOWN
